flood_tool/__init__.py
flood_tool/analysis.py
flood_tool/geo.py
flood_tool/live.py
flood_tool/mapping.py
flood_tool/tool.py
MSOIKKG-1.0.dist-info/METADATA
MSOIKKG-1.0.dist-info/WHEEL
MSOIKKG-1.0.dist-info/top_level.txt
MSOIKKG-1.0.dist-info/RECORD
